adafruit_circuitpython_display_shapes-2.10.4.dist-info/licenses/LICENSE
adafruit_display_shapes/__init__.py
adafruit_display_shapes/arc.py
adafruit_display_shapes/circle.py
adafruit_display_shapes/filled_polygon.py
adafruit_display_shapes/line.py
adafruit_display_shapes/multisparkline.py
adafruit_display_shapes/polygon.py
adafruit_display_shapes/rect.py
adafruit_display_shapes/roundrect.py
adafruit_display_shapes/sparkline.py
adafruit_display_shapes/triangle.py
adafruit_circuitpython_display_shapes-2.10.4.dist-info/METADATA
adafruit_circuitpython_display_shapes-2.10.4.dist-info/WHEEL
adafruit_circuitpython_display_shapes-2.10.4.dist-info/top_level.txt
adafruit_circuitpython_display_shapes-2.10.4.dist-info/RECORD
