Metadata-Version: 2.4
Name: adafruit-circuitpython-display_shapes
Version: 2.10.4
Summary: Various common shapes for use with displayio
Author-email: Adafruit Industries <circuitpython@adafruit.com>
License: MIT
Project-URL: Homepage, https://github.com/adafruit/Adafruit_CircuitPython_Display_Shapes
Keywords: adafruit,blinka,circuitpython,micropython,display_shapes,shapes,displayio,drawing
Classifier: Intended Audience :: Developers
Classifier: Topic :: Software Development :: Libraries
Classifier: Topic :: Software Development :: Embedded Systems
Classifier: Topic :: System :: Hardware
Classifier: License :: OSI Approved :: MIT License
Classifier: Programming Language :: Python :: 3
License-File: LICENSE
Requires-Dist: Adafruit-Blinka
Provides-Extra: optional
Dynamic: license-file
